src/VERSION
src/__init__.py
src/config.yml
src/pipeline.py
src/predict.py
src/train_pipeline.py
src/config/__init__.py
src/config/core.py
src/data/__init__.py
src/data/test.csv
src/data/train.csv
src/processing/__init__.py
src/processing/data_manager.py
src/processing/features.py
src/trained_models/__init__.py
src/trained_models/model_v0.0.7.pkl
end_to_end_ML_project-0.0.7.dist-info/METADATA
end_to_end_ML_project-0.0.7.dist-info/WHEEL
end_to_end_ML_project-0.0.7.dist-info/top_level.txt
end_to_end_ML_project-0.0.7.dist-info/RECORD
